[{"_path":"/blog/top-advantages-license-plate-recognition-parking-solutions","_dir":"blog","_draft":false,"_partial":false,"_locale":"","title":"The Top 5 Advantages of License Plate Recognition for Modern Parking Solutions","description":"In today's digital age, improving the efficiency and safety of parking management is more crucial than ever. License Plate Recognition (LPR) technology has emerged as a game-changing solution, providing numerous benefits for modern parking systems. This article explores the top five advantages of LPR technology, offering insights into how it enhances parking operations and safety.","_type":"markdown","_id":"content:blog:top-advantages-license-plate-recognition-parking-solutions.md","_source":"content","_file":"blog/top-advantages-license-plate-recognition-parking-solutions.md","_stem":"blog/top-advantages-license-plate-recognition-parking-solutions","_extension":"md","sitemap":{"loc":"/blog/top-advantages-license-plate-recognition-parking-solutions"}},{"_path":"/dir/airgarage","_dir":"dir","_draft":false,"_partial":false,"_locale":"","title":"AirGarage","description":"State-of-the-art software and systems including dynamic pricing and license plate recognition targeted for hotels and mixed-use spaces.","featured":false,"invert":false,"card_image":"5d55f8a49a649a59aab64b1c_airgarage-logo.png","tags":["Enforcement","Management Software","License Plate Recognition"],"_type":"markdown","_id":"content:dir:AirGarage.md","_source":"content","_file":"dir/AirGarage.md","_stem":"dir/AirGarage","_extension":"md","sitemap":{"loc":"/dir/airgarage"}}]